LICENSE
MANIFEST.in
README.rst
setup.py
crawlkits/__init__.py
crawlkits/toolkits.py
kinneykits.egg-info/PKG-INFO
kinneykits.egg-info/SOURCES.txt
kinneykits.egg-info/dependency_links.txt
kinneykits.egg-info/top_level.txt