Metadata-Version: 2.1
Name: kinneykits
Version: 1.0.0
Summary: This is a PyPackage that support some tools to python spider.
Home-page: https://gitee.com/miss-table/kinneykit
Author: kinney
Author-email: 3572484312@qq.com
License: MIT
License-File: LICENSE
